pyspac/__init__.py
pyspac/constants.py
pyspac/pyspac.py
pyspac-0.1.0.dist-info/licenses/LICENSE
pyspac-0.1.0.dist-info/METADATA
pyspac-0.1.0.dist-info/WHEEL
pyspac-0.1.0.dist-info/top_level.txt
pyspac-0.1.0.dist-info/RECORD
