Metadata-Version: 2.4
Name: pyspac
Version: 0.1.0
Summary: A library for fitting and analyzing asteroid phase curves.
Author-email: "Rodrigo C. Boufleur" <rcboufleur@gmail.com>
License: MIT
Project-URL: Homepage, https://github.com/rcboufleur/pySPAC
Project-URL: Bug Tracker, https://github.com/rcboufleur/pySPAC/issues
Classifier: Programming Language :: Python :: 3
Classifier: Operating System :: OS Independent
Classifier: Intended Audience :: Science/Research
Classifier: Topic :: Scientific/Engineering :: Astronomy
Requires-Python: >=3.6
License-File: LICENSE
Requires-Dist: numpy
Requires-Dist: lmfit
Requires-Dist: sbpy
Requires-Dist: tqdm
Dynamic: license-file
